.gitignore
.project
.pydevproject
Jenkinsfile
MANIFEST.in
README.md
build.parameters
setup.cfg
setup.py
youtube-dl-helper.desktop
bin/youtube-dl-helper
pixmaps/youtube-dl-helper.png
src/youtubedlhelper/__init__.py
src/youtubedlhelper/test_fake.py
youtube-dl-helper/youtube-dl-helper.glade
youtube_dl_helper.egg-info/PKG-INFO
youtube_dl_helper.egg-info/SOURCES.txt
youtube_dl_helper.egg-info/dependency_links.txt
youtube_dl_helper.egg-info/not-zip-safe
youtube_dl_helper.egg-info/top_level.txt