Metadata-Version: 1.1
Name: youtube-dl-helper
Version: 0.0.16
Summary: A tool to automate YouTube downloads via drag and drop
Home-page: http://github.com/Rudd-O/youtube-dl-helper
Author: Manuel Amador (Rudd-O)
Author-email: rudd-o@rudd-o.com
License: GPL
Keywords: YouTube download
Platform: UNKNOWN
Classifier: Development Status :: 5 - Production/Stable
Classifier: Environment :: X11 Applications :: GTK
Classifier: Intended Audience :: End Users/Desktop
Classifier: License :: OSI Approved :: GNU General Public License (GPL)
Classifier: Operating System :: POSIX :: Linux
Classifier: Programming Language :: Python :: 3 :: Only
Classifier: Programming Language :: Python :: 3.6
Classifier: Topic :: Communications :: File Sharing
Classifier: Topic :: Utilities
